{
  "slug": "stockholm-de",
  "source_book": "stockholm",
  "title": "Unter Freunden stirbt man nicht",
  "medium": "TV series",
  "country": "Germany",
  "year": 2021,
  "network": "Vox",
  "order": 2,
  "synopsis": "A television adaptation of Stockholm.",
  "still": {
    "image": "/images/stockholm-de.jpg",
    "position": "top"
  },
  "awards": [
    "Best Scripted Format · 2021 International Format Awards",
    "Best European Series · La Rochelle Festival De La Fiction 2021"
  ],
  "watch": [
    { "label": "Watch on YouTube", "url": "https://www.youtube.com/watch?v=pHSIM--ReGA", "primary": true },
    { "label": "YouTube clip", "url": "https://www.youtube.com/watch?v=yOJzNkKiAXM", "primary": false },
    { "label": "Watch on TVNow", "url": "https://www.tvnow.de/serien/unter-freunden-stirbt-man-nicht-19005/staffel-1/episode-1-annette-3822471", "primary": false }
  ],
  "info": [
    { "label": "IMDb", "url": "https://www.imdb.com/title/tt13413120/" },
    { "label": "Wikipedia (DE)", "url": "https://de.wikipedia.org/wiki/Unter_Freunden_stirbt_man_nicht" },
    { "label": "Tresor TV", "url": "https://www.tresor.tv/en/news/unter-freunden-stirbt-man-nicht-gewinnt-internationalen-tv-preis/" }
  ],
  "press": [
    { "label": "DWDL ratings", "url": "https://www.dwdl.de/zahlenzentrale/81960/auch_berben_lauterbach__co_koennen_bei_vox_nicht_punkten/" },
    { "label": "DWDL review", "url": "https://www.dwdl.de/meinungen/81971/unter_freunden_stirbt_man_nicht_haette_mehr_verdient/" }
  ]
}
